gandula/__init__.py
gandula/config.yaml
gandula/utils.py
gandula/core/__init__.py
gandula/core/config.py
gandula/core/logging.py
gandula/enrich/__init__.py
gandula/enrich/pff.py
gandula/html_templates/__init__.py
gandula/html_templates/video.jinja2
gandula/io/__init__.py
gandula/io/google_drive.py
gandula/io/reader.py
gandula/providers/__init__.py
gandula/providers/pff.py
gandula/providers/pff_gdrive_mapping.py
gandula/schemas/pff_events.py
gandula/schemas/pff_tracks.py
gandula/serializers/pff_event_deserializer.py
gandula/serializers/pff_event_helpers.py
gandula/serializers/pff_event_specification.py
gandula/transform/pff_events.py
gandula/transform/pff_events_mappings.py
gandula/transform/pff_tracks.py
gandula/validate/pff_events.py
gandula/validate/pff_tracks.py
gandula/view/__init__.py
gandula/view/event.py
gandula/view/frame.py
gandula/view/gif.py
gandula/view/pitch.py
gandula/view/png.py
gandula/view/video.py
gandula-0.3.1.dist-info/METADATA
gandula-0.3.1.dist-info/WHEEL
gandula-0.3.1.dist-info/licenses/LICENSE
gandula-0.3.1.dist-info/RECORD
