Metadata-Version: 2.4
Name: gandula
Version: 0.3.1
Summary: Gandula grabs football data and puts it back into play.
Project-URL: Home, https://github.com/SALabUFMG/gandula
Project-URL: Issues, https://github.com/SALabUFMG/gandula/issues
Author-email: Thiago Costa Porto <thiagocostaporto@gmail.com>, Ricardo Furbino <ricardofurbino@gmail.com>, Luiza Chagas <luiza.chagas@dcc.ufmg.br>, Leo Martins <leomartins@dcc.ufmg.br>
Maintainer-email: Thiago Costa Porto <thiagocostaporto@gmail.com>, Ricardo Furbino <ricardofurbino@gmail.com>
License: MIT License
License-File: LICENSE
Keywords: football,pff,sports analytics
Requires-Python: >=3.10
Requires-Dist: aiohttp>=3.10.5
Requires-Dist: fastparquet>=2024.11.0
Requires-Dist: fsspec>=2025.2.0
Requires-Dist: gdown>=5.2.0
Requires-Dist: gql>=3.5.0
Requires-Dist: imageio>=2.36.0
Requires-Dist: ipython>=8.26.0
Requires-Dist: ipywidgets>=8.1.5
Requires-Dist: jinja2>=3.1.4
Requires-Dist: jupyter>=1.0.0
Requires-Dist: kloppy>=3.16.0
Requires-Dist: matplotlib>=3.9.2
Requires-Dist: mplsoccer>=1.4.0
Requires-Dist: orjson>=3.10.7
Requires-Dist: pandas>=2.2.2
Requires-Dist: pydantic>=2.8.2
Requires-Dist: pygifsicle>=1.1.0
Requires-Dist: requests>=2.32.3
Requires-Dist: s3fs>=2025.2.0
Requires-Dist: selenium>=4.30.0
Requires-Dist: structlog>=24.4.0
Requires-Dist: torch-geometric>=2.6.1
Requires-Dist: torch>=2.6.0
Requires-Dist: tqdm>=4.66.5
